tocinator/__init__.py
tocinator/__main__.py
tocinator/tocinator.py
tocinator-1.0.2.dist-info/LICENSE.txt
tocinator-1.0.2.dist-info/METADATA
tocinator-1.0.2.dist-info/WHEEL
tocinator-1.0.2.dist-info/top_level.txt
tocinator-1.0.2.dist-info/RECORD
