Metadata-Version: 2.1
Name: tocinator
Version: 1.0.2
Summary: Generate a Table of Content from Markdown files.
Home-page: https://github.com/Coder-RG/tocinator
Author: Rishabh Goel
Author-email: rgoel1999@gmail.com
License: MIT
Platform: UNKNOWN
Classifier: Programming Language :: Python :: 3
Classifier: Programming Language :: Python :: 3.6
Classifier: Programming Language :: Python :: 3.7
Classifier: Programming Language :: Python :: 3.8
Classifier: Programming Language :: Python :: 3.9
Classifier: License :: OSI Approved :: MIT License
Classifier: Operating System :: OS Independent
Requires-Python: >=3.6
License-File: LICENSE.txt
